{
  "slug": "peer-vpc-with-transit-gateway-and-its-components",
  "title": "Peer VPC with Transit Gateway and its components",
  "level": "Advanced",
  "services": [
    "AWS"
  ],
  "summary": "",
  "duration": "01:15:00",
  "tasks": [
    {
      "title": "Task 1: Sign in to AWS Management Console",
      "steps": [
        {
          "text": "Click on the Open Console button, and you will get redirected to AWS Console in a new browser tab."
        },
        {
          "text": "On the AWS sign-in page,"
        },
        {
          "text": "Leave the Account ID as default. Never edit/remove the 12-digit Account ID present in the AWS Console. Otherwise, you cannot proceed with the lab."
        },
        {
          "text": "Now copy your User Name and Password in the Lab Console to the IAM Username and Password in AWS Console and click on the Sign in button."
        },
        {
          "text": "Once Signed In to the AWS Management Console, make the default AWS Region as US East (N. Virginia) us-east-1."
        }
      ]
    },
    {
      "title": "Task 2: Create the first VPC",
      "steps": [
        {
          "text": "In this task, we are going to create the first VPC (Virtual Private Cloud) in the specified AWS region. This VPC will serve as one of the VPCs that will be peered using the Transit Gateway."
        },
        {
          "text": "Make sure you are in the N.Virginia Region."
        },
        {
          "text": "Navigate to VPC by clicking on the Services menu in the top, then click on VPC in the Networking & Content Delivery section."
        },
        {
          "text": "Navigate to Your VPCs on the left panel and click on the Create VPC button."
        },
        {
          "text": "Select VPC only"
        },
        {
          "text": "Name tag : Enter First_VPC"
        },
        {
          "text": "IPv4 CIDR block : Enter 10.0.0.0/24"
        },
        {
          "text": "Leave everything else as default and click on the Create VPC button."
        },
        {
          "text": "You have successfully created the VPC. Note the VPC ID for later use."
        },
        {
          "text": "Now select the First_VPC from the list and click on the Actions dropdown and select Edit VPC Settings"
        },
        {
          "text": "Check the Enable DNS resolution and Enable DNS hostnames checkbox under DNS settings, and then click on the Save button."
        }
      ]
    },
    {
      "title": "Task 3: Create a Public subnet in First VPC",
      "steps": [
        {
          "text": "In this task, we are going to create a public subnet within the first VPC. The public subnet will be used for launching an EC2 instance that will be accessible over the internet."
        },
        {
          "text": "Navigate to Subnet from the left side menu and click on Create subnet button."
        },
        {
          "text": "VPC ID : Select the First_VPC VPC from the list."
        },
        {
          "text": "Subnet name : Enter Public_subnet_first_VPC"
        },
        {
          "text": "Availability Zone : Leave as No Preference"
        },
        {
          "text": "IPv4 CIDR block : Enter 10.0.0.0/25"
        },
        {
          "text": "Now click on the Create subnet button."
        }
      ]
    },
    {
      "title": "Task 4: Create and attach an Internet Gateway",
      "steps": [
        {
          "text": "In this task, we are going to create an internet gateway and attach it to the first VPC. The internet gateway allows the EC2 instance in the public subnet to communicate with the internet."
        },
        {
          "text": "Navigate to the Internet gateways from the left side menu and click on the Create Internet gateway button."
        },
        {
          "text": "Name tag : Enter IGW"
        },
        {
          "text": "Click on the Create Internet gateway button"
        },
        {
          "text": "Now click on the Actions dropdown and select Attach to VPC."
        },
        {
          "text": "Available VPCs : select First_VPC from the list."
        },
        {
          "text": "Now click on the Attach Internet gateway."
        }
      ]
    },
    {
      "title": "Task 5: Create a Public Route Table and associate it with the subnet",
      "steps": [
        {
          "text": "In this task, we are going to create a public route table and associate it with the public subnet. The route table controls the traffic between the subnet and the internet gateway."
        },
        {
          "text": "Navigate to Route tables on the left side panel and click on the Create route table."
        },
        {
          "text": "Name : Enter PublicRT"
        },
        {
          "text": "VPC* : Select the First_VPC from the list."
        },
        {
          "text": "Now click on the Create route table."
        },
        {
          "text": "Switch to the Subnet associations tab in below."
        },
        {
          "text": "Click on the Edit subnet associations."
        },
        {
          "text": "Now select the subnet with name Public_subnet_first_VPC and click on the Save associations button."
        }
      ]
    },
    {
      "title": "Task 6: Add public Route in the Route table",
      "steps": [
        {
          "text": "In this task, we are going to add a public route in the route table to allow traffic from the public subnet to the internet. This enables the EC2 instance in the public subnet to communicate with resources outside the VPC."
        },
        {
          "text": "Navigate to Route tables on the left side panel and select the PublicRT from the list."
        },
        {
          "text": "Switch to the Routes tab in below and click on the Edit routes."
        },
        {
          "text": "Now click on the Add route"
        },
        {
          "text": "Destination : Enter 0.0.0.0/0"
        },
        {
          "text": "Target : select Internet Gateway and then select the Internet Gateway id present."
        },
        {
          "text": "Click on the Save changes."
        }
      ]
    },
    {
      "title": "Task 7: Launch an EC2 instance in the First VPC",
      "steps": [
        {
          "text": "In this task, we are going to launch an EC2 instance in the first VPC's public subnet. This EC2 instance will be used to test the connectivity between the VPCs after peering them using the Transit Gateway."
        },
        {
          "text": "Make sure you are in the N. Virginia(us-east-1) Region."
        },
        {
          "text": "Navigate to EC2 by clicking on the Services menu in the top left, then click on EC2 in the Compute section."
        },
        {
          "text": "Navigate to Instances from the left side menu and click on Launch Instances button."
        },
        {
          "text": "Under the Name and tags section :"
        },
        {
          "text": "Name : First_VPCs_EC2"
        },
        {
          "text": "Under the Application and OS Images (Amazon Machine Image) section :"
        },
        {
          "text": "Select Quick Start tab and Amazon Linux 2023 kernel-6.1 AMI under it"
        },
        {
          "text": "Under the Instance Type section :"
        },
        {
          "text": "Instance Type : Select t2.micro"
        },
        {
          "text": "Under the Key Pair (login) section :"
        },
        {
          "text": "Click on Create new key pair hyperlink"
        },
        {
          "text": "Key pair name: ec2_ssh_key"
        },
        {
          "text": "Key pair type: RSA"
        },
        {
          "text": "Private key file format: .pem"
        },
        {
          "text": "Click on Create key pair and select the created key pair"
        },
        {
          "text": "Under the Network Settings section :"
        },
        {
          "text": "Click on Edit button"
        },
        {
          "text": "VPC : Select First_VPC"
        },
        {
          "text": "Subnet : leave as default"
        },
        {
          "text": "Auto-assign public IP: select Enable"
        },
        {
          "text": "Firewall (security groups) : Select Create a new security group"
        },
        {
          "text": "Security group name : Enter Public_EC2_SG"
        },
        {
          "text": "Description : Enter Security group for public EC2"
        },
        {
          "text": "To add SSH:"
        },
        {
          "text": "Choose Type: SSH"
        },
        {
          "text": "Source: Anywhere (From ALL IP addresses accessible)."
        },
        {
          "text": "For HTTP, click on Add security group rule,"
        },
        {
          "text": "Choose Type: HTTP"
        },
        {
          "text": "Source: Anywhere (From ALL IP addresses accessible)."
        },
        {
          "text": "For HTTPS, click on Add security group rule,"
        },
        {
          "text": "Choose Type: HTTPS"
        },
        {
          "text": "Source: Anywhere (From ALL IP addresses accessible)."
        },
        {
          "text": "Under the Advanced details section :"
        },
        {
          "text": "Under the IAM instance profile: Select task232_profile_... role."
        },
        {
          "text": "Under the User data: copy and paste the following script to create an HTML page served by an Apache httpd web server. Make sure you remove the extra space after pasting the comment."
        },
        {
          "text": "#!/bin/bash"
        },
        {
          "text": "sudo dnf update -y"
        },
        {
          "text": "sudo dnf install httpd -y"
        },
        {
          "text": "systemctl start httpd"
        },
        {
          "text": "systemctl enable httpd"
        },
        {
          "text": "echo \"<html><h1> Welcome to lab Public Server</h1><html>\" > /var/www/html/index.html"
        },
        {
          "text": "Keep everything else as default and click on the Launch instance button."
        },
        {
          "text": "Launch Status: Your instance is now launching, Navigate to Instances page from the left menu and wait until the status of the EC2 Instance changes to running."
        },
        {
          "text": "Note down the sample IPv4 Public IP Address of the EC2 instance. A sample is shown in the screenshot below."
        },
        {
          "text": "If you paste the IPv4 Public IP in your browser and hit [enter]. You will be able to the below webpage."
        }
      ]
    },
    {
      "title": "Task 8: Create a Second VPC",
      "steps": [
        {
          "text": "In this task, we are going to create the second VPC, which will be the other VPC that is peered with the first VPC using the Transit Gateway."
        },
        {
          "text": "Navigate to VPC by clicking on the Services menu at the top, then click on VPC in the Networking & Content Delivery section."
        },
        {
          "text": "Navigate to Your VPCs on the left panel and click on the Create VPC button."
        },
        {
          "text": "Select VPC only"
        },
        {
          "text": "Name tag : Enter Second_VPC"
        },
        {
          "text": "IPv4 CIDR block : Enter 20.0.0.0/24"
        },
        {
          "text": "Leave everything else as default and click on the Create VPC button."
        },
        {
          "text": "You have successfully created the VPC. Note the VPC ID for later use."
        },
        {
          "text": "Now select the Second_VPC from the list and click on the Actions and select Edit VPC settings"
        },
        {
          "text": "Check the Enable DNS resolution and Enable DNS hostnames checkbox under DNS settings and then click on the Save button"
        }
      ]
    },
    {
      "title": "Task 9: Create a Private subnet in Second VPC",
      "steps": [
        {
          "text": "In this task, we are going to create a private subnet within the second VPC. The private subnet will be used for launching an EC2 instance that will not have direct internet connectivity."
        },
        {
          "text": "Navigate to Subnets from the left side menu and click on Create Subnet button."
        },
        {
          "text": "VPC ID : Select the Second_VPC VPC from the list."
        },
        {
          "text": "Subnet name : Enter Private_subnet_second_VPC"
        },
        {
          "text": "Availability Zone : Leave as No Preference"
        },
        {
          "text": "IPv4 CIDR block : Enter 20.0.0.0/25"
        },
        {
          "text": "Now click on the Create subnet button"
        }
      ]
    },
    {
      "title": "Task 10: Launch an EC2 instance in Second VPC",
      "steps": [
        {
          "text": "In this task, we are going to launch an EC2 instance in the second VPC's private subnet. This EC2 instance will be used to test the connectivity between the VPCs after peering them using the Transit Gateway."
        },
        {
          "text": "Now again click on Launch Instances button."
        },
        {
          "text": "Under the Name and tags section :"
        },
        {
          "text": "Name : Second_VPCs_EC2"
        },
        {
          "text": "Under the Application and OS Images (Amazon Machine Image) section :"
        },
        {
          "text": "Select Quick Start tab and Amazon Linux 2023 kernel-6.1 AMI under it"
        },
        {
          "text": "Under the Instance Type section :"
        },
        {
          "text": "Instance Type : Select t2.micro"
        },
        {
          "text": "Under the Key Pair (login) section :"
        },
        {
          "text": "Select ec2_ssh_key from the list."
        },
        {
          "text": "Under the Network Settings section :"
        },
        {
          "text": "Click on Edit button"
        },
        {
          "text": "VPC : Select Second_VPC"
        },
        {
          "text": "Subnet : leave as default"
        },
        {
          "text": "Auto-assign public IP: select Disable"
        },
        {
          "text": "Firewall (security groups) : Select Create a new security group"
        },
        {
          "text": "Security group name : Enter Private_EC2_SG"
        },
        {
          "text": "Description : Enter Security group for private EC2"
        },
        {
          "text": "To add SSH:"
        },
        {
          "text": "Choose Type: SSH"
        },
        {
          "text": "Source: Anywhere (From ALL IP addresses accessible)."
        },
        {
          "text": "Keep everything else as default and then click on the Launch Instance button."
        },
        {
          "text": "Your instances are now launching. Navigate to the EC2 instance page and wait until the status changes to the Running. It will usually take 1-2 minutes."
        },
        {
          "text": "Since this EC2 is created in a private subnet, the machine will only have Private IP so, note down the sample IPv4 Private IP Address of the EC2 instance. A sample is shown in the screenshot below."
        }
      ]
    },
    {
      "title": "Task 11: Create a Transit gateway",
      "steps": [
        {
          "text": "In this task, we are going to create a Transit Gateway, which acts as a central hub for connecting multiple VPCs and on-premises networks. The Transit Gateway simplifies the network architecture and facilitates the peering between VPCs."
        },
        {
          "text": "Navigate to VPC by clicking on the Services menu at the top, then click on VPC in the Networking & Content Delivery section."
        },
        {
          "text": "Click on the Transit Gateways present under Transit Gateways section on the left sidebar."
        },
        {
          "text": "Click on the Create Transit gateway button to create a Transit gateway."
        },
        {
          "text": "Name tag: Enter DemoTG"
        },
        {
          "text": "Description: Enter TG for peering two VPCs"
        },
        {
          "text": "Keep all the options as default and click on Create transit gateway button."
        },
        {
          "text": "Currently, the status of the Transit gateway is in a pending state. It takes up to 5 minutes for it to become available."
        }
      ]
    },
    {
      "title": "Task 12: Create two Transit gateway attachment for the VPCs created",
      "steps": [
        {
          "text": "In this task, we are going to create two Transit Gateway attachments, one for each of the VPCs created. These attachments establish the peering between the VPCs and the Transit Gateway."
        },
        {
          "text": "Navigate to the Transit gateways attachments present under Transit Gateways section on the left side bar."
        },
        {
          "text": "Click on the Create transit gateway attachment button"
        },
        {
          "text": "Name tag : First_VPC_TGA"
        },
        {
          "text": "Transit Gateway ID: Select transit gateway present with Name tag DemoTG."
        },
        {
          "text": "Attachment type: Select VPC"
        },
        {
          "text": "DNS support: Checked (default)"
        },
        {
          "text": "IPv6 support: Unchecked"
        },
        {
          "text": "VPC ID: Select VPC with the Name First_VPC"
        },
        {
          "text": "Subnet IDs: Default"
        },
        {
          "text": "Click on the Create transit gateway attachment."
        },
        {
          "text": "Creation will be in-progress for the Transit gateway attachment."
        },
        {
          "text": "It takes upto 5 minutes for it to come in available state."
        },
        {
          "text": "To create the Transit gateway attachment for the second VPC, Click on the Create transit gateway attachment"
        },
        {
          "text": "Name tag: Second_VPCs_TGA"
        },
        {
          "text": "Transit Gateway ID: Select transit gateway present with Name tag DemoTG."
        },
        {
          "text": "Attachment type: Select VPC"
        },
        {
          "text": "DNS support: Checked (default)"
        },
        {
          "text": "IPv6 support: Unchecked"
        },
        {
          "text": "VPC ID: Select VPC with the Name Second_VPC"
        },
        {
          "text": "Subnet IDs: Default"
        },
        {
          "text": "Creation will be in-progress for the Transit gateway attachment."
        },
        {
          "text": "Once created both the Transit gateway attachment will be present."
        }
      ]
    },
    {
      "title": "Task 13: Add the routes in the First VPC’s route table",
      "steps": [
        {
          "text": "In this task, we are going to add a route in the first VPC's route table that directs traffic destined for the second VPC's CIDR range to the Transit Gateway. This enables communication between the VPCs through the Transit Gateway."
        },
        {
          "text": "Navigate to Route tables on the left side panel."
        },
        {
          "text": "There will be 4 route tables present, and to avoid confusion put the entry in the correct route table. Let's filter the route table present using the VPC filter."
        },
        {
          "text": "For the First VPC you created, you also have created a Route table with the name PublicRT which has a subnet association. Here the PublicRT route table is also called a custom or non-default route table."
        },
        {
          "text": "Click on the Route table ID to see the routes present."
        },
        {
          "text": "Click on the Routes tab below and click on the Edit routes."
        },
        {
          "text": "For this Route table, there are two entries present, First the local entry i.e. CIDR block of the First VPC, the second entry is about the route to the internet with Destination as 0.0.0.0/0 having target as the Internet gateway."
        },
        {
          "text": "Let’s add the third route which has destination as 20.0.0.0/24 i.e. CIDR range of second VPC and Target as Transit gateway."
        },
        {
          "text": "To add the third route, Click on the Add route."
        },
        {
          "text": "Destination: Enter 20.0.0.0/24"
        },
        {
          "text": "Target: Enter Transit Gateway"
        },
        {
          "text": "Click on the Save changes button."
        },
        {
          "text": "Make sure Routes have Destination as 20.0.0.0/24"
        },
        {
          "text": "Note: Sometimes it does not show the destination as 20.0.0.0/24, in that case, please add the following from Step 6 of this task."
        }
      ]
    },
    {
      "title": "Task 14: Add the routes in the Second VPC’s route table",
      "steps": [
        {
          "text": "In this task, we are going to add a route in the second VPC's route table that directs traffic destined for the first VPC's CIDR range to the Transit Gateway. This allows communication between the VPCs through the Transit Gateway."
        },
        {
          "text": "Navigate to Route tables on the left side panel."
        },
        {
          "text": "Filter the VPC’s by using the ID of the second VPC."
        },
        {
          "text": "In the second VPC, we have not created any extra route table, so there will be only one route table present which was created during the creation of VPC itself and it’s called a default route table or main route table."
        },
        {
          "text": "Let's filter the route table present using the VPC filter."
        },
        {
          "text": "To get the filter using the VPC option, simply click on the search bar and it will show the different options for the filter. Select VPC from that list and choose the ID of Second VPC."
        },
        {
          "text": "Click on the Route table ID to see the routes present."
        },
        {
          "text": "Click on the Routes tab in below and click on the Edit routes."
        },
        {
          "text": "There will be only one entry to local, as we have not created an internet gateway because this is a private route table."
        },
        {
          "text": "Let’s add the entry to 10.0.0.0/24 i.e. CIDR of the first VPC as a destination and Transit gateway as a target."
        },
        {
          "text": "To get the Transit gateway ID, click on the search button and select Transit Gateway from the list of options present."
        },
        {
          "text": "Click on the Save changes button."
        },
        {
          "text": "Make sure Routes have Destination as 10.0.0.0/24"
        },
        {
          "text": "Note: Sometimes it does not show the destination as 10.0.0.0/24, in that case, please add the following from Step 5 of this task."
        }
      ]
    },
    {
      "title": "Task 15: Test the connectivity between two VPCs",
      "steps": [
        {
          "text": "In this task, we are going to test the connectivity between the EC2 instances in both VPCs. This step confirms that the VPCs have been successfully peered using the Transit Gateway, and the EC2 instances can communicate with each other."
        },
        {
          "text": "You have copied the IPv4 Public IP of the EC2 instance created in the First VPC."
        },
        {
          "text": "Please follow the steps for the Session Manager to connect to First_VPCs_EC2"
        },
        {
          "text": "Select First_VPCs_EC2 and click on the Connect button."
        },
        {
          "text": "Go to SSM Session Manager and click Connect"
        },
        {
          "text": "Once you have successfully connected in to EC2, run the following commands :"
        },
        {
          "text": "Switch to root user :"
        },
        {
          "text": "sudo su"
        },
        {
          "text": "Update server repository :"
        },
        {
          "text": "sudo dnf update -y"
        },
        {
          "text": "Now we need to copy the .pem key of the EC2 instance created."
        },
        {
          "text": "Create a file :"
        },
        {
          "text": "nano ec2_ssh_key.pem"
        },
        {
          "text": "Open the .pem key of EC2 ec2_ssh_key in your local editor and paste it in the terminal file."
        },
        {
          "text": "Press [ctrl] + x / [control] + x"
        },
        {
          "text": "Press y key in your keyboard."
        },
        {
          "text": "File Name : No changes, press [Enter] key in your keyboard"
        },
        {
          "text": "Change the .pem key permission"
        },
        {
          "text": "chmod 400 ec2_ssh_key.pem"
        },
        {
          "text": "SSH into the Private EC2 ec2_ssh_key"
        },
        {
          "text": "ssh ec2-user@<IPv4 private Ip> -i ec2_ssh_key.pem"
        },
        {
          "text": "Copy the Private IP of Second_VPCs_EC2"
        },
        {
          "text": "Example : ssh ec2-user@20.0.0.11 -i ec2_ssh_key.pem"
        },
        {
          "text": "If the connection prompts a message to confirm connect enter yes"
        },
        {
          "text": "As you can see the IP address is changed to private ec2 private IP 30.0.1.154"
        },
        {
          "text": "Now you have connected two VPCs using the Transit gateway."
        },
        {
          "text": "Do You Know?"
        },
        {
          "text": "With Transit Gateway, you can easily add or remove VPC connections as your network grows or changes, without impacting existing connections. It provides a flexible and scalable solution for interconnecting VPCs and simplifies network administration, routing, and security."
        }
      ]
    },
    {
      "title": "Task 16: Validation Test",
      "steps": [
        {
          "text": "Once the lab steps are completed, please click on the Validation button on the left side panel."
        },
        {
          "text": "This will validate the resources in the AWS account and displays whether you have completed this lab successfully or not."
        },
        {
          "text": "Sample output :"
        }
      ]
    },
    {
      "title": "Task 17: Delete AWS Resources",
      "steps": [
        {
          "text": "Deleting EC2 Instances"
        },
        {
          "text": "Make sure you are in the US East (N. Virginia) Region."
        },
        {
          "text": "Navigate to EC2 by clicking on the Services menu in the top left, then click on EC2 in the Compute section."
        },
        {
          "text": "Now select both the EC2 instances that you have created, click on Instance State and click on the Terminate instance option."
        },
        {
          "text": "Click on the Terminate button and your EC2 will start terminating."
        },
        {
          "text": "Completion and Conclusion"
        },
        {
          "text": "You have successfully created a VPC with a public subnet & internet gateway and Launched an EC2 instance."
        },
        {
          "text": "You have successfully created a VPC with a private subnet and Launched an EC2 instance."
        },
        {
          "text": "You have successfully created the Transit gateway."
        },
        {
          "text": "You have successfully created the Transit gateway attachments for both the VPC’s."
        },
        {
          "text": "You have successfully tested the connectivity of VPC after peering using the Transit gateway."
        },
        {
          "text": "End Lab"
        },
        {
          "text": "Sign out of AWS Account."
        },
        {
          "text": "You have successfully completed the lab."
        },
        {
          "text": "Once you have completed the steps, click on End Lab from the lab console."
        }
      ]
    }
  ],
  "takeaways": [],
  "source": "course"
}
